aiojsonapi/__init__.py
aiojsonapi/client.py
aiojsonapi/config.py
aiojsonapi/dataclass.py
aiojsonapi/exception.py
aiojsonapi/middleware.py
aiojsonapi/request.py
aiojsonapi/response.py
aiojsonapi/routes.py
aiojsonapi/template.py
aiojsonapi-4.1.5.dist-info/WHEEL
aiojsonapi-4.1.5.dist-info/METADATA
aiojsonapi-4.1.5.dist-info/RECORD
