Metadata-Version: 2.1
Name: aiojsonapi
Version: 4.1.5
Summary: JSON aiohttp API constructor
License: MIT
Author: Yurzs
Author-email: yury@yurzs.dev
Requires-Python: >=3.7,<4.0
Classifier: License :: OSI Approved :: MIT License
Classifier: Programming Language :: Python :: 3
Classifier: Programming Language :: Python :: 3.7
Classifier: Programming Language :: Python :: 3.8
Classifier: Programming Language :: Python :: 3.9
Classifier: Programming Language :: Python :: 3.10
Classifier: Programming Language :: Python :: 3.11
Requires-Dist: aiohttp (>=3.8.3,<4.0.0)
Requires-Dist: pydantic (>=1.10.4,<2.0.0)
